{
    "key": "group_65bb77655bf44",
    "title": "CPT : Evènements",
    "fields": [
        {
            "key": "field_65bb77655e298",
            "label": "Date de début",
            "name": "start_date",
            "aria-label": "",
            "type": "date_picker",
            "instructions": "",
            "required": 0,
            "conditional_logic": 0,
            "wrapper": {
                "width": "",
                "class": "",
                "id": ""
            },
            "display_format": "d\/m\/Y",
            "return_format": "d\/m\/Y",
            "first_day": 1
        },
        {
            "key": "field_65bb77655e2ae",
            "label": "Date de fin",
            "name": "end_date",
            "aria-label": "",
            "type": "date_picker",
            "instructions": "",
            "required": 0,
            "conditional_logic": 0,
            "wrapper": {
                "width": "",
                "class": "",
                "id": ""
            },
            "display_format": "d\/m\/Y",
            "return_format": "d\/m\/Y",
            "first_day": 1
        },
        {
            "key": "field_65bb77655e2c4",
            "label": "Date limite d'inscription",
            "name": "limit_date",
            "aria-label": "",
            "type": "date_picker",
            "instructions": "",
            "required": 0,
            "conditional_logic": 0,
            "wrapper": {
                "width": "",
                "class": "",
                "id": ""
            },
            "display_format": "d\/m\/Y",
            "return_format": "d\/m\/Y",
            "first_day": 1
        },
        {
            "key": "field_65bb77655e2e1",
            "label": "Description",
            "name": "description",
            "aria-label": "",
            "type": "wysiwyg",
            "instructions": "",
            "required": 0,
            "conditional_logic": 0,
            "wrapper": {
                "width": "",
                "class": "",
                "id": ""
            },
            "default_value": "Vitae mauris eu dolor massa sapien mi at. Blandit dis ornare ut commodo enim id aliquam. Facilisis sit.",
            "tabs": "all",
            "toolbar": "full",
            "media_upload": 1,
            "delay": 0
        },
        {
            "key": "field_65bb77655e2e9",
            "label": "Titre court",
            "name": "short_title",
            "aria-label": "",
            "type": "text",
            "instructions": "",
            "required": 0,
            "conditional_logic": 0,
            "wrapper": {
                "width": "",
                "class": "",
                "id": ""
            },
            "default_value": "",
            "maxlength": "",
            "placeholder": "",
            "prepend": "",
            "append": ""
        },
        {
            "key": "field_65bb77655e2f2",
            "label": "Caractéristiques (Picto + texte)",
            "name": "custom_chars",
            "aria-label": "",
            "type": "repeater",
            "instructions": "",
            "required": 0,
            "conditional_logic": 0,
            "wrapper": {
                "width": "",
                "class": "",
                "id": ""
            },
            "layout": "table",
            "pagination": 0,
            "min": 0,
            "max": 2,
            "collapsed": "",
            "button_label": "Ajouter un élément",
            "rows_per_page": 20,
            "sub_fields": [
                {
                    "key": "field_65bb776564d7d",
                    "label": "Caractéristique",
                    "name": "characteristic",
                    "aria-label": "",
                    "type": "text",
                    "instructions": "",
                    "required": 0,
                    "conditional_logic": 0,
                    "wrapper": {
                        "width": "",
                        "class": "",
                        "id": ""
                    },
                    "default_value": "lorem ipsum dolor",
                    "maxlength": "",
                    "placeholder": "",
                    "prepend": "",
                    "append": "",
                    "parent_repeater": "field_65bb77655e2f2"
                },
                {
                    "key": "field_65bb776564d84",
                    "label": "Pictogramme",
                    "name": "picto",
                    "aria-label": "",
                    "type": "image",
                    "instructions": "",
                    "required": 0,
                    "conditional_logic": 0,
                    "wrapper": {
                        "width": "",
                        "class": "",
                        "id": ""
                    },
                    "return_format": "array",
                    "library": "all",
                    "min_width": "",
                    "min_height": "",
                    "min_size": "",
                    "max_width": "",
                    "max_height": "",
                    "max_size": "",
                    "mime_types": "",
                    "preview_size": "medium",
                    "parent_repeater": "field_65bb77655e2f2"
                }
            ]
        },
        {
            "key": "field_65dd8b28e051d",
            "label": "Libellé bouton de découverte",
            "name": "discover_event_label",
            "aria-label": "",
            "type": "text",
            "instructions": "",
            "required": 0,
            "conditional_logic": 0,
            "wrapper": {
                "width": "",
                "class": "",
                "id": ""
            },
            "default_value": "Découvrir l'évènement",
            "maxlength": "",
            "placeholder": "",
            "prepend": "",
            "append": ""
        },
        {
            "key": "field_65dd988f50985",
            "label": "Couleur associée à l'évènement",
            "name": "event_color",
            "aria-label": "",
            "type": "color_picker",
            "instructions": "",
            "required": 0,
            "conditional_logic": 0,
            "wrapper": {
                "width": "",
                "class": "",
                "id": ""
            },
            "default_value": "",
            "enable_opacity": 1,
            "return_format": "array"
        },
        {
            "key": "field_6639e723fe237",
            "label": "Lien alternatif",
            "name": "alternative_link",
            "aria-label": "",
            "type": "link",
            "instructions": "",
            "required": 0,
            "conditional_logic": 0,
            "wrapper": {
                "width": "",
                "class": "",
                "id": ""
            },
            "return_format": "array"
        }
    ],
    "location": [
        [
            {
                "param": "post_type",
                "operator": "==",
                "value": "events"
            }
        ]
    ],
    "menu_order": 0,
    "position": "normal",
    "style": "default",
    "label_placement": "top",
    "instruction_placement": "label",
    "hide_on_screen": "",
    "active": true,
    "description": "",
    "show_in_rest": 0,
    "modified": 1716986781
}
